<?xml version="1.0" encoding="utf-8"?>
<Loqui xmlns="http://tempuri.org/LoquiSource.xsd">
  <Object name="EnableParent" objType="Subrecord" recordType="XESP" GUID="38c30ba6-9e8b-4527-bc32-c50192765290" ID="299" >
    <Fields>
      <FormLink name="Reference" objType="Record">
        <Interface>ILinkedReference</Interface>
      </FormLink>
      <Break />
      <Enum name="Flags" enumName="EnableParent.Flag" byteLength="1" />
      <ByteArray name="Unknown" byteLength="3" hasBeenSet="False" />
    </Fields>
  </Object>
</Loqui>
